ds2viz/__init__.py
ds2viz/canvas.py
ds2viz/datastructures.py
ds2viz/default_styles.py
ds2viz/element.py
ds2viz/gizehengine.py
ds2viz/imageengine.py
ds2viz/primitive_styles.yaml
ds2viz/primitives.py
ds2viz/pygletengine.py
ds2viz/styles.py
ds2viz/svgengine.py
ds2viz/vector.py
ds2viz-0.1.4.dist-info/LICENSE
ds2viz-0.1.4.dist-info/METADATA
ds2viz-0.1.4.dist-info/WHEEL
ds2viz-0.1.4.dist-info/top_level.txt
ds2viz-0.1.4.dist-info/RECORD
