Metadata-Version: 2.1
Name: ds2viz
Version: 0.1.4
Summary: Don Sheehy's Data Structures Visualizations
Home-page: https://donsheehy.github.io/ds2viz
Author: Donald R. Sheehy
Author-email: don.r.sheehy@gmail.com
License: UNKNOWN
Platform: UNKNOWN
Classifier: Programming Language :: Python :: 3
Classifier: License :: OSI Approved :: MIT License
Classifier: Operating System :: OS Independent
Requires-Python: >=3.6
Requires-Dist: svgwrite
Requires-Dist: gizeh
Requires-Dist: PyYAML
